pymonke/__init__.py
pymonke/__main__.py
pymonke/py.typed
pymonke/fit/__init__.py
pymonke/fit/__misc.py
pymonke/fit/fit.py
pymonke/fit/fit_result.py
pymonke/fit/parse.py
pymonke/gui/__init__.py
pymonke/gui/app.py
pymonke/gui/browse_frame.py
pymonke/gui/dict_frame.py
pymonke/gui/entry_label_frame.py
pymonke/gui/info_label.py
pymonke/gui/labeled_entry.py
pymonke/gui/list_frame.py
pymonke/gui/main.py
pymonke/gui/misc.py
pymonke/gui/data_init/__init__.py
pymonke/gui/data_init/browse_save_frame.py
pymonke/gui/data_init/data_init_frame.py
pymonke/gui/data_init/status_frame.py
pymonke/gui/fitting/__init__.py
pymonke/gui/fitting/add_args_frame.py
pymonke/gui/fitting/fit_frame.py
pymonke/gui/fitting/fit_option_menu.py
pymonke/gui/formula/__init__.py
pymonke/gui/formula/formula_frame.py
pymonke/gui/formula/parameter_frame.py
pymonke/gui/formula/parameters_scrollable_frame.py
pymonke/gui/plot/__init__.py
pymonke/gui/plot/limits_frame.py
pymonke/gui/plot/misc_data_frame.py
pymonke/gui/plot/plot_canvas.py
pymonke/gui/plot/plot_frame.py
pymonke/latex/__init__.py
pymonke/latex/tex_table.py
pymonke/latex/utils.py
pymonke/latex/utils.pyi
pymonke/misc/__init__.py
pymonke/misc/benchmark.py
pymonke/misc/dataframe.py
pymonke/misc/file_management.py
pymonke/misc/pymonke_json_decoder.py
pymonke/misc/pymonke_json_encoder.py
pymonke/mmath/__init__.py
pymonke/mmath/rounding.py
pymonke/mmath/statistics.py
pymonke-0.1.2.1.dist-info/LICENSE
pymonke-0.1.2.1.dist-info/METADATA
pymonke-0.1.2.1.dist-info/WHEEL
pymonke-0.1.2.1.dist-info/top_level.txt
pymonke-0.1.2.1.dist-info/RECORD
