Metadata-Version: 2.1
Name: pymonke
Version: 0.1.2.1
Summary: Tools for creating lab reports and data analysis
Home-page: https://github.com/GabrielRemi/pymonke
Author: Gabriel Remiszewski
Classifier: Programming Language :: Python :: 3
Classifier: License :: OSI Approved :: MIT License
Classifier: Operating System :: OS Independent
Requires-Python: >=3.10
License-File: LICENSE
Requires-Dist: numpy >=1.26
Requires-Dist: pandas >=2.2
Requires-Dist: nltk >=3.8
Requires-Dist: matplotlib >=3.8
Requires-Dist: mypy-extensions >=1.0
Requires-Dist: scienceplots >=2.1
Requires-Dist: customtkinter >=5.2
Requires-Dist: scipy >=1.12
Requires-Dist: uncertainties >=3.1
